[
    {
        "url" : "http://boxofficemojo.com/movies/?id=riddick.htm"
    },
    {
        "url" : "http://boxofficemojo.com/movies/?id=insidious2.htm"
    },
    {
        "url" : "http://boxofficemojo.com/movies/?id=malavita.htm"
    },
    {
        "url" : "http://boxofficemojo.com/movies/?id=rush2013.htm"
    },
    {
        "url" : "http://boxofficemojo.com/movies/?id=prisoners.htm"
    },
    {
        "url" : "http://boxofficemojo.com/movies/?id=cloudy2.htm"
    },
    {
        "url" : "http://boxofficemojo.com/movies/?id=donjon.htm"
    },
    {
        "url" : "http://boxofficemojo.com/movies/?id=gravity.htm"
    },
    {
        "url" : "http://boxofficemojo.com/movies/?id=runnerrunner.htm"
    },
    {
        "url" : "http://boxofficemojo.com/movies/?id=captainphillips.htm"
    },
    {
        "url" : "http://boxofficemojo.com/movies/?id=machete2.htm"
    },
    {
        "url" : "http://boxofficemojo.com/movies/?id=romeoandjuliet2013.htm"
    },
    {
        "url" : "http://boxofficemojo.com/movies/?id=carrie2013.htm"
    },
    {
        "url" : "http://boxofficemojo.com/movies/?id=tomb.htm"
    },
    {
        "url" : "http://boxofficemojo.com/movies/?id=fifthestate.htm"
    },
    {
        "url" : "http://boxofficemojo.com/movies/?id=twelveyearsaslave.htm"
    },
    {
        "url" : "http://boxofficemojo.com/movies/?id=badgrandpa.htm"
    },
    {
        "url" : "http://boxofficemojo.com/movies/?id=counselor.htm"
    },
    {
        "url" : "http://boxofficemojo.com/movies/?id=endersgame.htm"
    },
    {
        "url" : "http://boxofficemojo.com/movies/?id=turkeys.htm"
    },
    {
        "url" : "http://boxofficemojo.com/movies/?id=diana.htm"
    },
    {
        "url" : "http://boxofficemojo.com/movies/?id=lastvegas.htm"
    },
    {
        "url" : "http://boxofficemojo.com/movies/?id=thor2.htm"
    },
    {
        "url" : "http://boxofficemojo.com/movies/?id=wolfofwallstreet.htm"
    },
    {
        "url" : "http://boxofficemojo.com/movies/?id=bookthief.htm"
    },
    {
        "url" : "http://boxofficemojo.com/movies/?id=catchingfire.htm"
    },
    {
        "url" : "http://boxofficemojo.com/movies/?id=deliveryman.htm"
    },
    {
        "url" : "http://boxofficemojo.com/movies/?id=frozen2013.htm"
    },
    {
        "url" : "http://boxofficemojo.com/movies/?id=oldboy2013.htm"
    },
    {
        "url" : "http://boxofficemojo.com/movies/?id=mandela2013.htm"
    },
    {
        "url" : "http://boxofficemojo.com/movies/?id=outofthefurnace.htm"
    },
    {
        "url" : "http://boxofficemojo.com/movies/?id=hobbit2.htm"
    },
    {
        "url" : "http://boxofficemojo.com/movies/?id=davido2013.htm"
    },
    {
        "url" : "http://boxofficemojo.com/movies/?id=savingmrbanks.htm"
    },
    {
        "url" : "http://boxofficemojo.com/movies/?id=anchorman2.htm"
    },
    {
        "url" : "http://boxofficemojo.com/movies/?id=jackryan.htm"
    },
    {
        "url" : "http://boxofficemojo.com/movies/?id=47ronin.htm"
    },
    {
        "url" : "http://boxofficemojo.com/movies/?id=waltermitty.htm"
    }
]
